fitspy/__init__.py
fitspy/__main__.py
fitspy/apps/__init__.py
fitspy/apps/interactive_bounds.py
fitspy/apps/pyside/__init__.py
fitspy/apps/pyside/main.py
fitspy/apps/pyside/main_controller.py
fitspy/apps/pyside/main_model.py
fitspy/apps/pyside/main_view.py
fitspy/apps/pyside/reset_settings.py
fitspy/apps/pyside/utils.py
fitspy/apps/pyside/components/__init__.py
fitspy/apps/pyside/components/about.py
fitspy/apps/pyside/components/custom_widgets.py
fitspy/apps/pyside/components/fit_stats.py
fitspy/apps/pyside/components/menubar.py
fitspy/apps/pyside/components/files/__init__.py
fitspy/apps/pyside/components/files/controller.py
fitspy/apps/pyside/components/files/dragndrop_list.py
fitspy/apps/pyside/components/files/maps_list.py
fitspy/apps/pyside/components/files/model.py
fitspy/apps/pyside/components/files/spectrum_list.py
fitspy/apps/pyside/components/plot/__init__.py
fitspy/apps/pyside/components/plot/controller.py
fitspy/apps/pyside/components/plot/map2d_plot.py
fitspy/apps/pyside/components/plot/model.py
fitspy/apps/pyside/components/plot/spectra_plot.py
fitspy/apps/pyside/components/plot/toolbar.py
fitspy/apps/pyside/components/settings/__init__.py
fitspy/apps/pyside/components/settings/baseline_table.py
fitspy/apps/pyside/components/settings/bkg_table.py
fitspy/apps/pyside/components/settings/controller.py
fitspy/apps/pyside/components/settings/generic_table.py
fitspy/apps/pyside/components/settings/model.py
fitspy/apps/pyside/components/settings/model_builder.py
fitspy/apps/pyside/components/settings/more_settings.py
fitspy/apps/pyside/components/settings/peaks_table.py
fitspy/apps/pyside/components/settings/status_box.py
fitspy/apps/tkinter/__init__.py
fitspy/apps/tkinter/callbacks.py
fitspy/apps/tkinter/gui.py
fitspy/apps/tkinter/toplevels.py
fitspy/apps/tkinter/utils.py
fitspy/core/__init__.py
fitspy/core/baseline.py
fitspy/core/baseline_methods.py
fitspy/core/migrations.py
fitspy/core/models.py
fitspy/core/models_bichromatic.py
fitspy/core/spectra.py
fitspy-2026.2.dist-info/licenses/LICENSE
fitspy-2026.2.dist-info/METADATA
fitspy-2026.2.dist-info/WHEEL
fitspy-2026.2.dist-info/entry_points.txt
fitspy-2026.2.dist-info/top_level.txt
fitspy-2026.2.dist-info/RECORD
