Metadata-Version: 2.4
Name: fitspy
Version: 2026.2
Summary: Fitspy: a generic tool to fit spectra in python
Author-email: Patrick Quéméré <patrick.quemere@cea.fr>, Killian Pavy <killian.pavy@cea.fr>
License: GPL v3
Project-URL: Homepage, https://github.com/CEA-MetroCarac/fitspy
Project-URL: Documentation, https://cea-metrocarac.github.io/fitspy/index.html
Keywords: Fitspy,fit,spectra,spectrum,map,1D,2D,decomposition,Gaussian,Lorentzian,Pseudovoigt,GUI
Classifier: Programming Language :: Python :: 3
Classifier: Programming Language :: Python :: 3.9
Classifier: Programming Language :: Python :: 3.10
Classifier: Programming Language :: Python :: 3.11
Classifier: License :: OSI Approved :: GNU General Public License v3 (GPLv3)
Classifier: Operating System :: Microsoft :: Windows
Classifier: Operating System :: POSIX :: Linux
Classifier: Operating System :: MacOS :: MacOS X
Classifier: Environment :: Console
Requires-Python: >=3.9
License-File: LICENSE
Requires-Dist: pyside6
Requires-Dist: numpy
Requires-Dist: pandas
Requires-Dist: matplotlib
Requires-Dist: scipy
Requires-Dist: lmfit
Requires-Dist: parse
Requires-Dist: dill
Requires-Dist: superqt[cmap]
Requires-Dist: pyqt-toast-notification
Requires-Dist: rosettasciio
Requires-Dist: h5py
Requires-Dist: pywin32; platform_system == "Windows"
Requires-Dist: pybaselines>=1.2.1
Provides-Extra: dev
Requires-Dist: pytest; extra == "dev"
Requires-Dist: pytest-mock; extra == "dev"
Requires-Dist: watchdog; extra == "dev"
Requires-Dist: esbonio; extra == "dev"
Requires-Dist: sphinx; extra == "dev"
Requires-Dist: doc8; extra == "dev"
Requires-Dist: rstcheck; extra == "dev"
Requires-Dist: sphinx-rtd-theme; extra == "dev"
Requires-Dist: sphinx-copybutton; extra == "dev"
Dynamic: license-file
